mailinabox_api/__init__.py
mailinabox_api/api_client.py
mailinabox_api/configuration.py
mailinabox_api/exceptions.py
mailinabox_api/rest.py
mailinabox_api/api/__init__.py
mailinabox_api/api/dns_api.py
mailinabox_api/api/mail_api.py
mailinabox_api/api/mfa_api.py
mailinabox_api/api/ssl_api.py
mailinabox_api/api/system_api.py
mailinabox_api/api/user_api.py
mailinabox_api/api/web_api.py
mailinabox_api/models/__init__.py
mailinabox_api/models/dns_custom_record.py
mailinabox_api/models/dns_custom_records_response.py
mailinabox_api/models/dns_dump_domain_record.py
mailinabox_api/models/dns_dump_domain_records.py
mailinabox_api/models/dns_dump_domains.py
mailinabox_api/models/dns_dump_response.py
mailinabox_api/models/dns_record_type.py
mailinabox_api/models/dns_secondary_nameserver_add_request.py
mailinabox_api/models/dns_secondary_nameserver_response.py
mailinabox_api/models/dns_update_request.py
mailinabox_api/models/dns_zones_response.py
mailinabox_api/models/mail_alias.py
mailinabox_api/models/mail_alias_by_domain.py
mailinabox_api/models/mail_alias_remove_request.py
mailinabox_api/models/mail_alias_upsert_request.py
mailinabox_api/models/mail_aliases_response_format.py
mailinabox_api/models/mail_user.py
mailinabox_api/models/mail_user_add_privilege_request.py
mailinabox_api/models/mail_user_add_request.py
mailinabox_api/models/mail_user_by_domain.py
mailinabox_api/models/mail_user_privilege.py
mailinabox_api/models/mail_user_remove_privilege_request.py
mailinabox_api/models/mail_user_remove_request.py
mailinabox_api/models/mail_user_set_password_request.py
mailinabox_api/models/mail_user_status.py
mailinabox_api/models/mail_users_response.py
mailinabox_api/models/mail_users_response_format.py
mailinabox_api/models/me_auth_status.py
mailinabox_api/models/me_response.py
mailinabox_api/models/mfa_disable_request.py
mailinabox_api/models/mfa_enable_request.py
mailinabox_api/models/mfa_status_response.py
mailinabox_api/models/mfa_status_response_enabled_mfa.py
mailinabox_api-0.51.1.dist-info/METADATA
mailinabox_api-0.51.1.dist-info/WHEEL
mailinabox_api-0.51.1.dist-info/top_level.txt
mailinabox_api-0.51.1.dist-info/RECORD
