Metadata-Version: 2.1
Name: mailinabox-api
Version: 0.51.1
Summary: Mail-in-a-Box
Home-page: https://github.com/badsyntax/mailinabox-api-py
Author: Richard Willis
Author-email: willis.rh@gmail.com
License: CC0 1.0 Universal
Keywords: mailinabox,mail-in-a-box,Mail-in-a-Box
Platform: UNKNOWN
Requires-Dist: urllib3 (>=1.15)
Requires-Dist: six (>=1.10)
Requires-Dist: certifi
Requires-Dist: python-dateutil
